grammar_to_regex/__init__.py
grammar_to_regex/cfg2regex.py
grammar_to_regex/grammar_to_regular.py
grammar_to_regex/helpers.py
grammar_to_regex/regex.py
grammar_to_regex/type_defs.py
grammar_to_regex-1.0.1.dist-info/LICENSE
grammar_to_regex-1.0.1.dist-info/METADATA
grammar_to_regex-1.0.1.dist-info/WHEEL
grammar_to_regex-1.0.1.dist-info/top_level.txt
grammar_to_regex-1.0.1.dist-info/RECORD
