Metadata-Version: 2.1
Name: grammar_to_regex
Version: 1.0.1
Summary: Conversion of a (sub) grammar to (approximated) regular expressions.
Author-email: Dominic Steinhöfel <dominic.steinhoefel@cispa.de>
License: GNU GENERAL PUBLIC LICENSE
Project-URL: Homepage, https://github.com/rindPHI/grammar2regex/
Project-URL: Bug Tracker, https://github.com/rindPHI/grammar2regex/issues
Classifier: Intended Audience :: Science/Research
Classifier: License :: OSI Approved :: GNU General Public License v3 (GPLv3)
Classifier: Programming Language :: Python :: 3
Classifier: Operating System :: OS Independent
Classifier: Topic :: Scientific/Engineering
Requires-Python: >=3.10
License-File: LICENSE
Requires-Dist: pydot >=1.4.2
Requires-Dist: wheel >=0.37.1
Requires-Dist: z3-solver >=4.8.17.0
Provides-Extra: test
Requires-Dist: fuzzingbook >=1.1 ; extra == 'test'
Requires-Dist: pytest-cov >=3.0.0 ; extra == 'test'
Requires-Dist: pytest-forked >=1.3.0 ; extra == 'test'
Requires-Dist: pytest-html >=3.1.1 ; extra == 'test'
Requires-Dist: pytest-profiling >=1.7.0 ; extra == 'test'
Requires-Dist: pytest-pycharm >=0.7.0 ; extra == 'test'
Requires-Dist: pytest-rerunfailures >=10.2 ; extra == 'test'
Requires-Dist: pytest-xdist >=2.4.0 ; extra == 'test'
Requires-Dist: pytest >=7.1.2 ; extra == 'test'
